netbox_subsystems/__init__.py
netbox_subsystems/admin.py
netbox_subsystems/api/__init__.py
netbox_subsystems/api/nested_serializers.py
netbox_subsystems/api/serializers.py
netbox_subsystems/api/urls.py
netbox_subsystems/api/views.py
netbox_subsystems/filtersets.py
netbox_subsystems/forms.py
netbox_subsystems/migrations/0002_supersetuser_embeddeddashboard.py
netbox_subsystems/migrations/__init__.py
netbox_subsystems/models.py
netbox_subsystems/navigation.py
netbox_subsystems/search.py
netbox_subsystems/tables.py
netbox_subsystems/template_content.py
netbox_subsystems/templates/netbox_subsystems/subsystem.html
netbox_subsystems/templates/netbox_subsystems/subsystem_edit.html
netbox_subsystems/templates/netbox_subsystems/subsystem_include.html
netbox_subsystems/templates/netbox_subsystems/subsystems_objects.html
netbox_subsystems/templates/netbox_subsystems/system.html
netbox_subsystems/templates/netbox_subsystems/system_edit.html
netbox_subsystems/templates/netbox_subsystems/system_include.html
netbox_subsystems/templates/netbox_subsystems/systemgroup.html
netbox_subsystems/templates/netbox_subsystems/systemgroup_edit.html
netbox_subsystems/templates/netbox_subsystems/systemgroup_include.html
netbox_subsystems/templates/netbox_subsystems/systems_edit.html
netbox_subsystems/urls.py
netbox_subsystems/views.py
netbox_subsystems-0.3.0.dist-info/LICENSE
netbox_subsystems-0.3.0.dist-info/METADATA
netbox_subsystems-0.3.0.dist-info/WHEEL
netbox_subsystems-0.3.0.dist-info/RECORD
